pyrime/__init__.py
pyrime/__main__.py
pyrime/api.cpython-314-x86_64-linux-musl.so
pyrime/api.pyi
pyrime/key.py
pyrime/py.typed
pyrime/rime.py
pyrime/session.py
pyrime/utils.py
pyrime/assets/json/keys.json
pyrime/assets/json/modifiers.json
pyrime/ime/__init__.py
pyrime/ime/ime.py
pyrime/ime/key.py
pyrime/ime/ui.py
pyrime/nvim/__init__.py
pyrime/nvim/keymap.py
pyrime/nvim/rime.py
pyrime/nvim/win.py
pyrime/ptpython/formatted_text.py
pyrime/ptpython/gdb.py
pyrime/ptpython/ime.py
pyrime/ptpython/layout.py
pyrime/ptpython/rime.py
pyrime/ptpython/bindings/__init__.py
pyrime/ptpython/bindings/autocorrect.py
pyrime/ptpython/bindings/autoinsert.py
pyrime/ptpython/bindings/autopair.py
pyrime/ptpython/bindings/autosuggestion.py
pyrime/ptpython/bindings/extra.py
pyrime/ptpython/bindings/rime.py
pyrime/ptpython/bindings/smartinput.py
pyrime/ptpython/bindings/viemacs.py
pyrime/ptpython/utils/ansi.py
pyrime/ptpython/utils/prompt_style.py
pyrime.libs/libgcc_s-0cd532bd.so.1
pyrime.libs/libgflags-6bcb6c53.so.2.2.2
pyrime.libs/libglog-a97d28fb.so.0.7.1
pyrime.libs/libleveldb-0ace9b71.so.1.23.0
pyrime.libs/liblzma-9cee5efb.so.5.8.1
pyrime.libs/libmarisa-09a5e983.so.0.0.0
pyrime.libs/libopencc-50b2d6be.so.1.1.9
pyrime.libs/librime-f4845722.so.1.13.1
pyrime.libs/libsnappy-f36b9e28.so.1.2.2
pyrime.libs/libstdc++-5d72f927.so.6.0.33
pyrime.libs/libunwind-3ebecdab.so.8.1.0
pyrime.libs/libyaml-cpp-711a3110.so.0.8.0
pyrime-0.2.1.dist-info/METADATA
pyrime-0.2.1.dist-info/WHEEL
pyrime-0.2.1.dist-info/RECORD
