Metadata-Version: 2.1
Name: pyrime
Version: 0.2.1
Summary: rime for python, attached to prompt-toolkit keybindings for some prompt-toolkit applications such as ptpython
Keywords: rime,ptpython,prompt-toolkit
Author-Email: "Wu, Zhenyu" <wuzhenyu@ustc.edu>
License: GPL v3
Classifier: Development Status :: 3 - Alpha
Classifier: Intended Audience :: Developers
Classifier: Topic :: Software Development :: Build Tools
Classifier: License :: OSI Approved :: GNU General Public License v3 (GPLv3)
Classifier: Operating System :: Microsoft :: Windows
Classifier: Operating System :: POSIX
Classifier: Operating System :: Unix
Classifier: Operating System :: MacOS
Classifier: Programming Language :: Python :: 3 :: Only
Classifier: Programming Language :: Python :: 3
Classifier: Programming Language :: Python :: 3.11
Classifier: Programming Language :: Python :: 3.12
Classifier: Programming Language :: Python :: 3.13
Classifier: Programming Language :: Python :: Implementation :: CPython
Classifier: Programming Language :: Python :: Implementation :: PyPy
Project-URL: Homepage, https://pyrime.readthedocs.io
Project-URL: Download, https://github.com/rimeinn/pyrime/releases
Project-URL: Bug Report, https://github.com/rimeinn/pyrime/issues
Project-URL: Source, https://github.com/rimeinn/pyrime
Requires-Python: >=3.11
Requires-Dist: platformdirs
Requires-Dist: wcwidth
Provides-Extra: cli
Requires-Dist: getch; extra == "cli"
Provides-Extra: color
Requires-Dist: colorama; extra == "color"
Provides-Extra: dev
Requires-Dist: pytest-cov; extra == "dev"
Requires-Dist: prompt-toolkit; extra == "dev"
Provides-Extra: prompt-toolkit
Requires-Dist: prompt-toolkit; extra == "prompt-toolkit"
Provides-Extra: ptpython
Requires-Dist: ptpython; extra == "ptpython"
Provides-Extra: nvim
Requires-Dist: pynvim; extra == "nvim"
